samplelib
