Metadata-Version: 2.1
Name: test-sayhello
Version: 0.0.2
Summary: Learning python modules
Home-page: UNKNOWN
Author: Prathamesh Sable
Author-email: prathameshks2003@gmail.com
License: UNKNOWN
Keywords: python,hello,test_sayhello
Platform: UNKNOWN
Classifier: Development Status :: 1 - Planning
Classifier: Intended Audience :: Developers
Classifier: Programming Language :: Python :: 3
Classifier: Operating System :: Unix
Classifier: Operating System :: MacOS :: MacOS X
Classifier: Operating System :: Microsoft :: Windows
License-File: LICENSE
